{"max_network_wait": 10, "network_wait_for_all_actions": true, "wait_buffer": 0.2, "410579e1-c957-41d9-b25c-91ac8457c707_0": {"0": {"operation_intent": "navigate to 'https://orange-hrm.lambdatestinternal.com/orangehrm-5.7' website", "operation_type": "OPEN", "url": "https://orange-hrm.lambdatestinternal.com/orangehrm-5.7", "instruction_id": "fa251a063ea644c5ae4ccff9de7fbdca", "operation_id": "2adf7afea53f4e6f", "optional_flag": false, "max_retries": 0, "retries_delay": 0, "explicit_wait": 0, "implicit_wait": 0, "frame": "", "user_variables": "[]", "operation_start": "2025-09-13 14:32:20.034519", "operation_end": "2025-09-13 14:32:23.281470", "instruction_module_id": "410579e1-c957-41d9-b25c-91ac8457c707", "instruction_module_name": "OrangeHRM Login Module", "use_v2_mobile_tagging": false, "hard_assertion": false, "dialog_action": "", "dismiss_dialog": false, "is_coordinates_used_for_interaction": false, "element_coordinates_ratio": [], "element_bounds_ratio": [], "kaneaiMobileTaggingImageLimit": 1, "clicks_order_code": "se_js_ac", "selector": "", "manual_interaction_tag": "", "is_global_variable": false, "is_global_variable_persist": false, "global_variable_id": "", "mobile_browser": false, "wait_for_element_timeout": 0, "failure_condition": "", "parent_instruction_id": "", "sub_instruction_obj": "{\"operation\": \"navigate to 'https://orange-hrm.lambdatestinternal.com/orangehrm-5.7' website\", \"thought\": \"Navigate the browser to the specified URL 'https://orange-hrm.lambdatestinternal.com/orangehrm-5.7'.\", \"agent\": \"Operation Agent\", \"operation_dict\": {\"operation_type\": \"OPEN\", \"url\": \"https://orange-hrm.lambdatestinternal.com/orangehrm-5.7\", \"operation_intent\": \"navigate to 'https://orange-hrm.lambdatestinternal.com/orangehrm-5.7' website\"}, \"params\": {}, \"secrets\": {}, \"variable\": {}}", "_original_index": 0, "global_operation_index": 0, "module_version": 1.1}, "1": {"operation_intent": "Query 'Username input box' visibility", "locator": ["//html/body/div/div[1]/div/div[1]/div/div[2]/div[2]/form/div[1]/div/div[2]/input"], "operation_type": "VISUAL_QUERY", "query_variable_name": "username_input_box_visible", "query_info_dict": {"name": "Username input box", "type": "Web Element", "attributes_dict": {}, "selected_attribute_name": "displayed", "use_prompt_query_response": false, "custom_data_hook_flag": false, "custom_data_hook_name": ""}, "use_query_v2": true, "vision_query_url": "https://kaneai-api.lambdatest.com", "version": "v1", "instruction_id": "664681c34fcc4d49bc7247e5de182e05", "operation_id": "8a90688bbcf0426d", "optional_flag": false, "max_retries": 0, "retries_delay": 0, "explicit_wait": 0, "implicit_wait": 0, "frame": "[]", "user_variables": "[]", "operation_start": "2025-09-13 14:32:33.703381", "operation_end": "2025-09-13 14:32:33.750347", "instruction_module_id": "410579e1-c957-41d9-b25c-91ac8457c707", "instruction_module_name": "OrangeHRM Login Module", "use_v2_mobile_tagging": false, "hard_assertion": false, "dialog_action": "", "dismiss_dialog": false, "is_coordinates_used_for_interaction": false, "element_coordinates_ratio": [], "element_bounds_ratio": [], "kaneaiMobileTaggingImageLimit": 1, "clicks_order_code": "se_js_ac", "selector": {"frameInfo": [], "locators": [{"isXPath": false, "score": 90, "selector": "[placeholder=\"Username\"][name=\"username\"]"}, {"isXPath": false, "score": 85, "selector": "[placeholder=\"Username\"]"}, {"isXPath": false, "score": 85, "selector": "[name=\"username\"]"}, {"isXPath": true, "score": 85, "selector": "//input[@placeholder='Username' and @name='username']"}, {"isXPath": false, "score": 80, "selector": ".oxd-input--focus"}, {"isXPath": true, "score": 50, "selector": "//input[starts-with(@placeholder,'Usern')]"}, {"isXPath": true, "score": 40, "selector": "//input[contains(@class,'oxd-input--focus')]"}, {"isXPath": true, "score": 40, "selector": "//input[contains(@placeholder,'Username')]"}]}, "manual_interaction_tag": "", "is_global_variable": false, "is_global_variable_persist": false, "global_variable_id": "", "mobile_browser": false, "wait_for_element_timeout": 0, "failure_condition": "", "parent_instruction_id": "", "sub_instruction_obj": "{\"operation\": \"Query 'Username input box' visibility\", \"thought\": \"Check if the 'Username input box' is visible on the viewport.\", \"agent\": \"Vision Agent\", \"operation_dict\": {\"operation_type\": \"VISION_QUERY\", \"variable_name\": \"username_input_box_visible\", \"element\": \"Username input box\", \"operation_intent\": \"Query 'Username input box' visibility\"}, \"params\": {}, \"secrets\": {}, \"variable\": {}}", "_original_index": 1, "global_operation_index": 1, "module_version": 1.1}, "2": {"operation_intent": "set the value of variable 'assertion_operand_664681c34fcc4d49bc7247e5de182e05_0' to true", "operation_type": "SET_VARIABLE", "instruction_id": "664681c34fcc4d49bc7247e5de182e05", "operation_id": "da6738cd341c4c28", "optional_flag": false, "max_retries": 0, "retries_delay": 0, "explicit_wait": 0, "implicit_wait": 0, "frame": "", "user_variables": "[{\"name\": \"assertion_operand_664681c34fcc4d49bc7247e5de182e05_0\", \"value\": \"true\", \"value_type\": \"string\"}]", "operation_start": "2025-09-13 14:32:34.639364", "operation_end": "2025-09-13 14:32:34.750069", "instruction_module_id": "410579e1-c957-41d9-b25c-91ac8457c707", "instruction_module_name": "OrangeHRM Login Module", "use_v2_mobile_tagging": false, "hard_assertion": false, "dialog_action": "", "dismiss_dialog": false, "is_coordinates_used_for_interaction": false, "element_coordinates_ratio": [], "element_bounds_ratio": [], "kaneaiMobileTaggingImageLimit": 1, "clicks_order_code": "se_js_ac", "selector": "", "manual_interaction_tag": "", "is_global_variable": false, "is_global_variable_persist": false, "global_variable_id": "", "mobile_browser": false, "wait_for_element_timeout": 0, "failure_condition": "", "parent_instruction_id": "", "sub_instruction_obj": "{\"operation\": \"set the value of variable 'assertion_operand_664681c34fcc4d49bc7247e5de182e05_0' to true\", \"thought\": \"Setting the value of variable 'assertion_operand_664681c34fcc4d49bc7247e5de182e05_0' to true requires setting the value of the variable, which can be done by the Operation Agent.\", \"agent\": \"Operation Agent\", \"operation_dict\": {\"operation_type\": \"SET_VARIABLE\", \"variable_name\": \"assertion_operand_664681c34fcc4d49bc7247e5de182e05_0\", \"variable_value\": \"true\", \"operation_intent\": \"set the value of variable 'assertion_operand_664681c34fcc4d49bc7247e5de182e05_0' to true\"}, \"params\": {}, \"secrets\": {}, \"variable\": {}}", "_original_index": 2, "global_operation_index": 2, "module_version": 1.1}, "3": {"operation_intent": "Assert 'Username input box' is visible", "operation_type": "ASSERTION", "assertion_tree": {"operator": "equals", "left_operand": {"username_input_box_visible": "runtime_variable"}, "right_operand": {"assertion_operand_664681c34fcc4d49bc7247e5de182e05_0": "runtime_variable"}, "transform_operands": []}, "use_assertion_v2": true, "query_variable_name": "", "assertion": "Assert 'Username input box' is visible", "string_to_float": false, "operator": [""], "expected_value": "", "instruction_id": "664681c34fcc4d49bc7247e5de182e05", "operation_id": "3852b42acb3b4c81", "optional_flag": false, "max_retries": 0, "retries_delay": 0, "explicit_wait": 0, "implicit_wait": 0, "frame": "", "user_variables": "[]", "operation_start": "2025-09-13 14:32:35.640663", "operation_end": "2025-09-13 14:32:36.005442", "instruction_module_id": "410579e1-c957-41d9-b25c-91ac8457c707", "instruction_module_name": "OrangeHRM Login Module", "use_v2_mobile_tagging": false, "hard_assertion": false, "dialog_action": "", "dismiss_dialog": false, "is_coordinates_used_for_interaction": false, "element_coordinates_ratio": [], "element_bounds_ratio": [], "kaneaiMobileTaggingImageLimit": 1, "clicks_order_code": "se_js_ac", "selector": "", "manual_interaction_tag": "", "is_global_variable": false, "is_global_variable_persist": false, "global_variable_id": "", "mobile_browser": false, "wait_for_element_timeout": 0, "failure_condition": "Fail test immediately", "parent_instruction_id": "", "sub_instruction_obj": "{\"operation\": \"Assert 'Username input box' is visible\", \"thought\": \"Verify the 'Username input box' is visible on the viewport.\", \"agent\": \"Operation Agent\", \"operation_dict\": {\"operation_type\": \"ASSERTION\", \"assertion_tree\": {\"operator\": \"equals\", \"left_operand\": {\"username_input_box_visible\": \"runtime_variable\"}, \"right_operand\": {\"assertion_operand_664681c34fcc4d49bc7247e5de182e05_0\": \"runtime_variable\"}, \"transform_operands\": []}, \"operation_intent\": \"Assert 'Username input box' is visible\"}, \"params\": {\"assertion_tree\": {\"operator\": \"equals\", \"left_operand\": {\"username_input_box_visible\": \"runtime_variable\"}, \"right_operand\": {\"assertion_operand_664681c34fcc4d49bc7247e5de182e05_0\": \"runtime_variable\"}, \"transform_operands\": []}, \"operation_intent\": \"Assert 'Username input box' is visible\"}, \"secrets\": {}, \"variable\": {}}", "_original_index": 3, "global_operation_index": 3, "module_version": 1.1}, "4": {"operation_intent": "type 'pushpa.raj' in Username", "locator": ["//html/body/div/div[1]/div/div[1]/div/div[2]/div[2]/form/div[1]/div/div[2]/input"], "operation_type": "TYPE", "value": "pushpa.raj", "multiple_inputs": false, "instruction_id": "8142bd4f96744919af58fed3f97e018b", "operation_id": "1a4999000f744508", "optional_flag": false, "max_retries": 0, "retries_delay": 0, "explicit_wait": 0, "implicit_wait": 0, "frame": "[]", "user_variables": "[]", "operation_start": "2025-09-13 14:32:43.089362", "operation_end": "2025-09-13 14:32:44.199507", "instruction_module_id": "410579e1-c957-41d9-b25c-91ac8457c707", "instruction_module_name": "OrangeHRM Login Module", "use_v2_mobile_tagging": false, "hard_assertion": false, "dialog_action": "", "dismiss_dialog": false, "is_coordinates_used_for_interaction": false, "element_coordinates_ratio": [], "element_bounds_ratio": [], "kaneaiMobileTaggingImageLimit": 1, "clicks_order_code": "se_js_ac", "selector": {"frameInfo": [], "locators": [{"isXPath": false, "score": 90, "selector": "[placeholder=\"Username\"][name=\"username\"]"}, {"isXPath": false, "score": 85, "selector": "[placeholder=\"Username\"]"}, {"isXPath": false, "score": 85, "selector": "[name=\"username\"]"}, {"isXPath": true, "score": 85, "selector": "//input[@placeholder='Username' and @name='username']"}, {"isXPath": false, "score": 80, "selector": ".oxd-input--focus"}, {"isXPath": true, "score": 50, "selector": "//input[starts-with(@placeholder,'Usern')]"}, {"isXPath": true, "score": 40, "selector": "//input[contains(@class,'oxd-input--focus')]"}, {"isXPath": true, "score": 40, "selector": "//input[contains(@placeholder,'Username')]"}]}, "manual_interaction_tag": "", "is_global_variable": false, "is_global_variable_persist": false, "global_variable_id": "", "mobile_browser": false, "wait_for_element_timeout": 0, "failure_condition": "", "parent_instruction_id": "", "sub_instruction_obj": "{\"operation\": \"type 'pushpa.raj' in Username\", \"thought\": \"Enter the value 'pushpa.raj' into the 'Username' field.\", \"agent\": \"Vision Agent\", \"operation_dict\": {\"operation_type\": \"TYPE\", \"value\": \"pushpa.raj\", \"element\": \"Username\", \"operation_intent\": \"type 'pushpa.raj' in Username\"}, \"params\": {}, \"secrets\": {}, \"variable\": {}}", "_original_index": 4, "global_operation_index": 4, "module_version": 1.1}, "5": {"operation_intent": "type ******************* in Password input field", "locator": ["//html/body/div/div[1]/div/div[1]/div/div[2]/div[2]/form/div[2]/div/div[2]/input"], "operation_type": "TYPE", "value": "0NkLWCMXdAnZ45LJ@#2", "multiple_inputs": false, "instruction_id": "07834cdfae4c433da233bc83ac660968", "operation_id": "39c1d864eea441bc", "optional_flag": false, "max_retries": 0, "retries_delay": 0, "explicit_wait": 0, "implicit_wait": 0, "frame": "[]", "user_variables": "[]", "operation_start": "2025-09-13 14:32:51.493845", "operation_end": "2025-09-13 14:32:52.651782", "instruction_module_id": "410579e1-c957-41d9-b25c-91ac8457c707", "instruction_module_name": "OrangeHRM Login Module", "use_v2_mobile_tagging": false, "hard_assertion": false, "dialog_action": "", "dismiss_dialog": false, "is_coordinates_used_for_interaction": false, "element_coordinates_ratio": [], "element_bounds_ratio": [], "kaneaiMobileTaggingImageLimit": 1, "clicks_order_code": "se_js_ac", "selector": {"frameInfo": [], "locators": [{"isXPath": true, "score": 95, "selector": "//input[@name='password' and @type='password']"}, {"isXPath": false, "score": 90, "selector": "[placeholder=\"Password\"][name=\"password\"]"}, {"isXPath": false, "score": 90, "selector": "[placeholder=\"Password\"][type=\"password\"]"}, {"isXPath": false, "score": 90, "selector": "[name=\"password\"][type=\"password\"]"}, {"isXPath": false, "score": 85, "selector": "[placeholder=\"Password\"]"}, {"isXPath": true, "score": 85, "selector": "//input[@placeholder='Password' and @type='password']"}, {"isXPath": true, "score": 85, "selector": "//input[@placeholder='Password' and @name='password']"}, {"isXPath": true, "score": 40, "selector": "//input[contains(@placeholder,'Password')]"}]}, "manual_interaction_tag": "", "is_global_variable": false, "is_global_variable_persist": false, "global_variable_id": "", "mobile_browser": false, "wait_for_element_timeout": 0, "failure_condition": "", "parent_instruction_id": "", "sub_instruction_obj": "{\"operation\": \"type '0NkLWCMXdAnZ45LJ@#2' in Password\", \"thought\": \"Enter the given password into the Password field.\", \"agent\": \"Vision Agent\", \"operation_dict\": {\"operation_type\": \"TYPE\", \"value\": \"0NkLWCMXdAnZ45LJ@#2\", \"element\": \"Password\", \"operation_intent\": \"type '0NkLWCMXdAnZ45LJ@#2' in Password\"}, \"params\": {}, \"secrets\": {}, \"variable\": {}}", "_original_index": 5, "global_operation_index": 5, "module_version": 1.1}, "6": {"operation_intent": "Click 'Login'", "locator": ["//html/body/div/div[1]/div/div[1]/div/div[2]/div[2]/form/div[3]/button"], "operation_type": "CLICK", "value": "", "instruction_id": "0bc094be536945849837999c0998b63c", "operation_id": "da5e698b1082448c", "optional_flag": false, "max_retries": 0, "retries_delay": 0, "explicit_wait": 0, "implicit_wait": 0, "frame": "[]", "user_variables": "[]", "operation_start": "2025-09-13 14:32:59.522278", "operation_end": "2025-09-13 14:33:02.690445", "instruction_module_id": "410579e1-c957-41d9-b25c-91ac8457c707", "instruction_module_name": "OrangeHRM Login Module", "use_v2_mobile_tagging": false, "hard_assertion": false, "dialog_action": "", "dismiss_dialog": false, "is_coordinates_used_for_interaction": false, "element_coordinates_ratio": [], "element_bounds_ratio": [], "kaneaiMobileTaggingImageLimit": 1, "clicks_order_code": "se_js_ac", "selector": {"frameInfo": [], "locators": [{"isXPath": false, "score": 85, "selector": "[type=\"submit\"]"}, {"isXPath": false, "score": 80, "selector": ".oxd-button--medium"}, {"isXPath": false, "score": 80, "selector": ".oxd-button--main"}, {"isXPath": false, "score": 80, "selector": ".oxd-button--medium.oxd-button--main"}, {"isXPath": true, "score": 50, "selector": "//button[starts-with(@type,'submi')]"}, {"isXPath": true, "score": 40, "selector": "//button[contains(@class,'oxd-button--medium')]"}, {"isXPath": true, "score": 40, "selector": "//button[contains(@type,'submit')]"}, {"isXPath": true, "score": 40, "selector": "//button[contains(@class,'oxd-button--main')]"}]}, "manual_interaction_tag": "", "is_global_variable": false, "is_global_variable_persist": false, "global_variable_id": "", "mobile_browser": false, "wait_for_element_timeout": 0, "failure_condition": "", "parent_instruction_id": "", "sub_instruction_obj": "{\"operation\": \"Click 'Login'\", \"thought\": \"Tap the element labeled 'Login'.\", \"agent\": \"Vision Agent\", \"operation_dict\": {\"operation_type\": \"CLICK\", \"element\": \"Login\", \"operation_intent\": \"Click 'Login'\"}, \"params\": {}, \"secrets\": {}, \"variable\": {}}", "_original_index": 6, "global_operation_index": 6, "module_version": 1.1}, "7": {"operation_intent": "wait 3 seconds", "operation_type": "WAIT", "value": 3, "instruction_id": "a4a70f6974a344e99048fc422bd2b446", "operation_id": "0b64fed223d44c5a", "optional_flag": false, "max_retries": 0, "retries_delay": 0, "explicit_wait": 0, "implicit_wait": 0, "frame": "", "user_variables": "[]", "operation_start": "2025-09-13 14:33:06.646753", "operation_end": "2025-09-13 14:33:09.959745", "instruction_module_id": "410579e1-c957-41d9-b25c-91ac8457c707", "instruction_module_name": "OrangeHRM Login Module", "use_v2_mobile_tagging": false, "hard_assertion": false, "dialog_action": "", "dismiss_dialog": false, "is_coordinates_used_for_interaction": false, "element_coordinates_ratio": [], "element_bounds_ratio": [], "kaneaiMobileTaggingImageLimit": 1, "clicks_order_code": "se_js_ac", "selector": "", "manual_interaction_tag": "", "is_global_variable": false, "is_global_variable_persist": false, "global_variable_id": "", "mobile_browser": false, "wait_for_element_timeout": 0, "failure_condition": "", "parent_instruction_id": "", "sub_instruction_obj": "{\"operation\": \"wait 3 seconds\", \"thought\": \"Pause execution for '3' seconds as requested.\", \"agent\": \"Operation Agent\", \"operation_dict\": {\"operation_type\": \"WAIT\", \"duration\": 3, \"operation_intent\": \"wait 3 seconds\"}, \"params\": {}, \"secrets\": {}, \"variable\": {}}", "_original_index": 7, "global_operation_index": 7, "module_version": 1.1}}, "main_flow": {"0": {"operation_intent": "Click 'PIM'", "locator": ["//html/body/div/div[1]/div[1]/aside/nav/div[2]/ul/li[2]/a"], "operation_type": "CLICK", "value": "", "instruction_id": "230885be21f643d6b1f2638af8318c23", "operation_id": "ff4b2521bba74afb", "optional_flag": false, "max_retries": 0, "retries_delay": 0, "explicit_wait": 0, "implicit_wait": 0, "frame": "[]", "user_variables": "[]", "operation_start": "2025-09-13 14:33:17.204824", "operation_end": "2025-09-13 14:33:20.125471", "instruction_module_id": "", "instruction_module_name": "", "use_v2_mobile_tagging": false, "hard_assertion": false, "dialog_action": "", "dismiss_dialog": false, "is_coordinates_used_for_interaction": false, "element_coordinates_ratio": [], "element_bounds_ratio": [], "kaneaiMobileTaggingImageLimit": 1, "clicks_order_code": "se_js_ac", "selector": {"frameInfo": [], "locators": [{"isXPath": true, "score": 70, "selector": "//nav[@role='navigation' and @aria-label='Sidepanel']/div[2]/ul[1]/li[2]/a[1]"}, {"isXPath": true, "score": 70, "selector": "//nav[@role='navigation' and @aria-label='Sidepanel']/div[2]/ul[1]/li[2]/a[1]"}, {"isXPath": false, "score": 35, "selector": "[aria-label=\"Sidepanel\"] > div:nth-child(2) > ul:nth-child(2) > li:nth-child(2) > a:nth-child(1)"}, {"isXPath": false, "score": 35, "selector": "[aria-label=\"Sidepanel\"] > div:nth-child(2) > ul:nth-child(2) > li:nth-child(2) > a:nth-child(1)"}]}, "manual_interaction_tag": "", "is_global_variable": false, "is_global_variable_persist": false, "global_variable_id": "", "mobile_browser": false, "wait_for_element_timeout": 0, "failure_condition": "", "parent_instruction_id": "", "sub_instruction_obj": "{\"operation\": \"Click 'PIM'\", \"thought\": \"Tap the element labeled 'PIM' on the page.\", \"agent\": \"Vision Agent\", \"operation_dict\": {\"operation_type\": \"CLICK\", \"element\": \"PIM\", \"operation_intent\": \"Click 'PIM'\"}, \"params\": {}, \"secrets\": {}, \"variable\": {}}", "_original_index": 8, "global_operation_index": 8}, "1": {"operation_intent": "wait 3 seconds", "operation_type": "WAIT", "value": 3, "instruction_id": "bf37ae4fe6b34dda8f2b98865728d07c", "operation_id": "02c4621998e245e8", "optional_flag": false, "max_retries": 0, "retries_delay": 0, "explicit_wait": 0, "implicit_wait": 0, "frame": "", "user_variables": "[]", "operation_start": "2025-09-13 14:33:22.920446", "operation_end": "2025-09-13 14:33:26.224776", "instruction_module_id": "", "instruction_module_name": "", "use_v2_mobile_tagging": false, "hard_assertion": false, "dialog_action": "", "dismiss_dialog": false, "is_coordinates_used_for_interaction": false, "element_coordinates_ratio": [], "element_bounds_ratio": [], "kaneaiMobileTaggingImageLimit": 1, "clicks_order_code": "se_js_ac", "selector": "", "manual_interaction_tag": "", "is_global_variable": false, "is_global_variable_persist": false, "global_variable_id": "", "mobile_browser": false, "wait_for_element_timeout": 0, "failure_condition": "", "parent_instruction_id": "", "sub_instruction_obj": "{\"operation\": \"wait 3 seconds\", \"thought\": \"Pause execution for '3' seconds as instructed.\", \"agent\": \"Operation Agent\", \"operation_dict\": {\"operation_type\": \"WAIT\", \"duration\": 3, \"operation_intent\": \"wait 3 seconds\"}, \"params\": {}, \"secrets\": {}, \"variable\": {}}", "_original_index": 9, "global_operation_index": 9}, "2": {"operation_intent": "Click 'Reports'", "locator": ["//html/body/div/div[1]/div[1]/header/div[2]/nav/ul/li[4]/a"], "operation_type": "CLICK", "value": "", "instruction_id": "dfe00248fc444847850c32137dd27c3a", "operation_id": "cd3f988f11b24f2c", "optional_flag": false, "max_retries": 0, "retries_delay": 0, "explicit_wait": 0, "implicit_wait": 0, "frame": "[]", "user_variables": "[]", "operation_start": "2025-09-13 14:33:33.581622", "operation_end": "2025-09-13 14:33:35.480529", "instruction_module_id": "", "instruction_module_name": "", "use_v2_mobile_tagging": false, "hard_assertion": false, "dialog_action": "", "dismiss_dialog": false, "is_coordinates_used_for_interaction": false, "element_coordinates_ratio": [], "element_bounds_ratio": [], "kaneaiMobileTaggingImageLimit": 1, "clicks_order_code": "se_js_ac", "selector": {"frameInfo": [], "locators": [{"isXPath": true, "score": 70, "selector": "//nav[@role='navigation' and @aria-label='Topbar Menu']/ul[1]/li[4]/a[1]"}, {"isXPath": true, "score": 70, "selector": "//nav[@role='navigation' and @aria-label='Topbar Menu']/ul[1]/li[4]/a[1]"}, {"isXPath": true, "score": 65, "selector": "//a[text()='Reports']"}, {"isXPath": true, "score": 50, "selector": "//a[contains(text(),'Reports')]"}, {"isXPath": false, "score": 35, "selector": "[aria-label=\"Topbar Menu\"] > ul:nth-child(1) > li:nth-child(4) > a:nth-child(1)"}, {"isXPath": false, "score": 35, "selector": "[aria-label=\"Topbar Menu\"] > ul:nth-child(1) > li:nth-child(4) > a:nth-child(1)"}]}, "manual_interaction_tag": "", "is_global_variable": false, "is_global_variable_persist": false, "global_variable_id": "", "mobile_browser": false, "wait_for_element_timeout": 0, "failure_condition": "", "parent_instruction_id": "", "sub_instruction_obj": "{\"operation\": \"Click 'Reports'\", \"thought\": \"Tap the element labeled 'Reports'.\", \"agent\": \"Vision Agent\", \"operation_dict\": {\"operation_type\": \"CLICK\", \"element\": \"Reports\", \"operation_intent\": \"Click 'Reports'\"}, \"params\": {}, \"secrets\": {}, \"variable\": {}}", "_original_index": 10, "global_operation_index": 10}, "3": {"operation_intent": "wait 3 seconds", "operation_type": "WAIT", "value": 3, "instruction_id": "35f9f99f0ed3435e9c8772eed6e17b7a", "operation_id": "9d442b7e40634d87", "optional_flag": false, "max_retries": 0, "retries_delay": 0, "explicit_wait": 0, "implicit_wait": 0, "frame": "", "user_variables": "[]", "operation_start": "2025-09-13 14:33:38.135633", "operation_end": "2025-09-13 14:33:41.427671", "instruction_module_id": "", "instruction_module_name": "", "use_v2_mobile_tagging": false, "hard_assertion": false, "dialog_action": "", "dismiss_dialog": false, "is_coordinates_used_for_interaction": false, "element_coordinates_ratio": [], "element_bounds_ratio": [], "kaneaiMobileTaggingImageLimit": 1, "clicks_order_code": "se_js_ac", "selector": "", "manual_interaction_tag": "", "is_global_variable": false, "is_global_variable_persist": false, "global_variable_id": "", "mobile_browser": false, "wait_for_element_timeout": 0, "failure_condition": "", "parent_instruction_id": "", "sub_instruction_obj": "{\"operation\": \"wait 3 seconds\", \"thought\": \"Pause execution for '3' seconds as requested.\", \"agent\": \"Operation Agent\", \"operation_dict\": {\"operation_type\": \"WAIT\", \"duration\": 3, \"operation_intent\": \"wait 3 seconds\"}, \"params\": {}, \"secrets\": {}, \"variable\": {}}", "_original_index": 11, "global_operation_index": 11}, "4": {"operation_intent": "type 'test' in report name section", "locator": ["//html/body/div/div[1]/div[2]/div[2]/div/div[1]/div[2]/form/div[1]/div/div/div/div[2]/div/div/input"], "operation_type": "TYPE", "value": "test", "multiple_inputs": false, "instruction_id": "7bfce078db7c407493e0021a3baf2a98", "operation_id": "acc24bf7ec544f10", "optional_flag": false, "max_retries": 0, "retries_delay": 0, "explicit_wait": 0, "implicit_wait": 0, "frame": "[]", "user_variables": "[]", "operation_start": "2025-09-13 14:33:56.569083", "operation_end": "2025-09-13 14:33:57.849199", "instruction_module_id": "", "instruction_module_name": "", "use_v2_mobile_tagging": false, "hard_assertion": false, "dialog_action": "", "dismiss_dialog": false, "is_coordinates_used_for_interaction": false, "element_coordinates_ratio": [], "element_bounds_ratio": [], "kaneaiMobileTaggingImageLimit": 1, "clicks_order_code": "se_js_ac", "selector": {"frameInfo": [], "locators": [{"isXPath": false, "score": 85, "selector": "[placeholder=\"Type for hints...\"]"}, {"isXPath": false, "score": 70, "selector": ".oxd-autocomplete-text-input--before + input"}, {"isXPath": false, "score": 70, "selector": "input:has(+ .oxd-autocomplete-text-input--after)"}, {"isXPath": false, "score": 55, "selector": ".oxd-input-field-bottom-space > div:nth-child(2) > div:nth-child(1) > div:nth-child(1) > input:nth-child(2)"}, {"isXPath": true, "score": 50, "selector": "//input[starts-with(@placeholder,'Type ')]"}, {"isXPath": true, "score": 30, "selector": "//input[contains(@placeholder,'Type for hints...')]"}, {"isXPath": true, "score": 15, "selector": "//div[contains(@class,'oxd-input-field-bottom-space')]/div[2]/div[1]/div[1]/input[1]"}, {"isXPath": true, "score": 15, "selector": "//div[contains(@class,'oxd-input-field-bottom-space')]/div[2]/div[1]/div[1]/input[1]"}]}, "manual_interaction_tag": "", "is_global_variable": false, "is_global_variable_persist": false, "global_variable_id": "", "mobile_browser": false, "wait_for_element_timeout": 0, "failure_condition": "", "parent_instruction_id": "", "sub_instruction_obj": "{\"operation\": \"type 'test' in report name section\", \"thought\": \"Enter the value 'test' into the 'report name section'.\", \"agent\": \"Vision Agent\", \"operation_dict\": {\"operation_type\": \"TYPE\", \"value\": \"test\", \"element\": \"report name section\", \"operation_intent\": \"type 'test' in report name section\"}, \"params\": {}, \"secrets\": {}, \"variable\": {}}", "_original_index": 12, "global_operation_index": 12}, "5": {"operation_intent": "Click 'Search'", "locator": ["//html/body/div/div[1]/div[2]/div[2]/div/div[1]/div[2]/form/div[2]/button[2]"], "operation_type": "CLICK", "value": "", "instruction_id": "3765af3109f54f86b7177cded25fc49a", "operation_id": "77969e44546d420f", "optional_flag": false, "max_retries": 0, "retries_delay": 0, "explicit_wait": 0, "implicit_wait": 0, "frame": "[]", "user_variables": "[]", "operation_start": "2025-09-13 14:34:06.108121", "operation_end": "2025-09-13 14:34:06.748867", "instruction_module_id": "", "instruction_module_name": "", "use_v2_mobile_tagging": false, "hard_assertion": false, "dialog_action": "", "dismiss_dialog": false, "is_coordinates_used_for_interaction": false, "element_coordinates_ratio": [], "element_bounds_ratio": [], "kaneaiMobileTaggingImageLimit": 1, "clicks_order_code": "se_js_ac", "selector": {"frameInfo": [], "locators": [{"isXPath": false, "score": 85, "selector": "[type=\"submit\"]"}, {"isXPath": false, "score": 70, "selector": ".oxd-button--ghost + button"}, {"isXPath": false, "score": 70, "selector": ".oxd-button--medium.oxd-button--ghost + button"}, {"isXPath": true, "score": 70, "selector": "//div[@id='app']/div[1]/div[2]/div[2]/div[1]/div[1]/div[2]/form[1]/div[2]/button[2]"}, {"isXPath": false, "score": 65, "selector": "#app > div:nth-child(1) > div:nth-child(2) > div:nth-child(2) > div:nth-child(1) > div:nth-child(1) > div:nth-child(3) > form:nth-child(1) > div:nth-child(3) > button:nth-child(2)"}, {"isXPath": true, "score": 50, "selector": "//button[starts-with(@type,'submi')]"}, {"isXPath": true, "score": 40, "selector": "//button[contains(@type,'submit')]"}]}, "manual_interaction_tag": "", "is_global_variable": false, "is_global_variable_persist": false, "global_variable_id": "", "mobile_browser": false, "wait_for_element_timeout": 0, "failure_condition": "", "parent_instruction_id": "", "sub_instruction_obj": "{\"operation\": \"Click 'Search'\", \"thought\": \"Tap the element labeled 'Search'.\", \"agent\": \"Vision Agent\", \"operation_dict\": {\"operation_type\": \"CLICK\", \"element\": \"Search\", \"operation_intent\": \"Click 'Search'\"}, \"params\": {}, \"secrets\": {}, \"variable\": {}}", "_original_index": 13, "global_operation_index": 13}, "6": {"operation_intent": "Query 'invalid' text visibility", "locator": ["//html/body/div/div[1]/div[2]/div[2]/div/div[1]/div[2]/form/div[1]/div/div/div/span"], "operation_type": "VISUAL_QUERY", "query_variable_name": "invalid_visible", "query_info_dict": {"name": "'Invalid' text", "type": "Web Element", "attributes_dict": {}, "selected_attribute_name": "displayed", "use_prompt_query_response": false, "custom_data_hook_flag": false, "custom_data_hook_name": ""}, "use_query_v2": true, "vision_query_url": "https://kaneai-api.lambdatest.com", "version": "v1", "instruction_id": "98817bc0b00a4987a0d5826472439c6f", "operation_id": "3be6aeca88124e61", "optional_flag": false, "max_retries": 0, "retries_delay": 0, "explicit_wait": 0, "implicit_wait": 0, "frame": "[]", "user_variables": "[]", "operation_start": "2025-09-13 14:34:32.059795", "operation_end": "2025-09-13 14:34:32.165689", "instruction_module_id": "", "instruction_module_name": "", "use_v2_mobile_tagging": false, "hard_assertion": false, "dialog_action": "", "dismiss_dialog": false, "is_coordinates_used_for_interaction": false, "element_coordinates_ratio": [], "element_bounds_ratio": [], "kaneaiMobileTaggingImageLimit": 1, "clicks_order_code": "se_js_ac", "selector": {"frameInfo": [], "locators": [{"isXPath": false, "score": 80, "selector": ".oxd-input-field-error-message"}, {"isXPath": false, "score": 80, "selector": ".oxd-text--span.oxd-input-field-error-message"}, {"isXPath": false, "score": 80, "selector": ".oxd-input-field-bottom-space > span"}, {"isXPath": false, "score": 75, "selector": ".oxd-input-field-bottom-space > span:nth-child(3)"}, {"isXPath": true, "score": 65, "selector": "//span[text()='Invalid']"}, {"isXPath": true, "score": 30, "selector": "//span[contains(@class,'oxd-input-field-error-message')]"}, {"isXPath": true, "score": 30, "selector": "//div[contains(@class,'oxd-input-field-bottom-space')]/span[1]"}, {"isXPath": true, "score": 25, "selector": "//span[contains(@class,'oxd-text--span') and contains(@class,'oxd-input-field-error-message')]"}]}, "manual_interaction_tag": "", "is_global_variable": false, "is_global_variable_persist": false, "global_variable_id": "", "mobile_browser": false, "wait_for_element_timeout": 0, "failure_condition": "", "parent_instruction_id": "", "sub_instruction_obj": "{\"operation\": \"Query 'invalid' text visibility\", \"thought\": \"Check if the text 'invalid' is visible on the viewport.\", \"agent\": \"Vision Agent\", \"operation_dict\": {\"operation_type\": \"VISION_QUERY\", \"variable_name\": \"invalid_visible\", \"element\": \"invalid\", \"operation_intent\": \"Query 'invalid' text visibility\"}, \"params\": {}, \"secrets\": {}, \"variable\": {}}", "_original_index": 14, "global_operation_index": 14}, "7": {"operation_intent": "set the value of variable 'assertion_operand_98817bc0b00a4987a0d5826472439c6f_0' to true", "operation_type": "SET_VARIABLE", "instruction_id": "98817bc0b00a4987a0d5826472439c6f", "operation_id": "28c296edcce74d6f", "optional_flag": false, "max_retries": 0, "retries_delay": 0, "explicit_wait": 0, "implicit_wait": 0, "frame": "", "user_variables": "[{\"name\": \"assertion_operand_98817bc0b00a4987a0d5826472439c6f_0\", \"value\": \"true\", \"value_type\": \"string\"}]", "operation_start": "2025-09-13 14:34:33.110789", "operation_end": "2025-09-13 14:34:33.232134", "instruction_module_id": "", "instruction_module_name": "", "use_v2_mobile_tagging": false, "hard_assertion": false, "dialog_action": "", "dismiss_dialog": false, "is_coordinates_used_for_interaction": false, "element_coordinates_ratio": [], "element_bounds_ratio": [], "kaneaiMobileTaggingImageLimit": 1, "clicks_order_code": "se_js_ac", "selector": "", "manual_interaction_tag": "", "is_global_variable": false, "is_global_variable_persist": false, "global_variable_id": "", "mobile_browser": false, "wait_for_element_timeout": 0, "failure_condition": "", "parent_instruction_id": "", "sub_instruction_obj": "{\"operation\": \"set the value of variable 'assertion_operand_98817bc0b00a4987a0d5826472439c6f_0' to true\", \"thought\": \"Setting the value of variable 'assertion_operand_98817bc0b00a4987a0d5826472439c6f_0' to true requires setting the value of the variable, which can be done by the Operation Agent.\", \"agent\": \"Operation Agent\", \"operation_dict\": {\"operation_type\": \"SET_VARIABLE\", \"variable_name\": \"assertion_operand_98817bc0b00a4987a0d5826472439c6f_0\", \"variable_value\": \"true\", \"operation_intent\": \"set the value of variable 'assertion_operand_98817bc0b00a4987a0d5826472439c6f_0' to true\"}, \"params\": {}, \"secrets\": {}, \"variable\": {}}", "_original_index": 15, "global_operation_index": 15}, "8": {"operation_intent": "Assert 'invalid' text is visible on the viewport", "operation_type": "ASSERTION", "assertion_tree": {"operator": "equals", "left_operand": {"invalid_visible": "runtime_variable"}, "right_operand": {"assertion_operand_98817bc0b00a4987a0d5826472439c6f_0": "runtime_variable"}, "transform_operands": []}, "use_assertion_v2": true, "query_variable_name": "", "assertion": "Assert 'invalid' text is visible on the viewport", "string_to_float": false, "operator": [""], "expected_value": "", "instruction_id": "98817bc0b00a4987a0d5826472439c6f", "operation_id": "85390fc692484d1b", "optional_flag": false, "max_retries": 0, "retries_delay": 0, "explicit_wait": 0, "implicit_wait": 0, "frame": "", "user_variables": "[]", "operation_start": "2025-09-13 14:34:34.094738", "operation_end": "2025-09-13 14:34:34.475098", "instruction_module_id": "", "instruction_module_name": "", "use_v2_mobile_tagging": false, "hard_assertion": false, "dialog_action": "", "dismiss_dialog": false, "is_coordinates_used_for_interaction": false, "element_coordinates_ratio": [], "element_bounds_ratio": [], "kaneaiMobileTaggingImageLimit": 1, "clicks_order_code": "se_js_ac", "selector": "", "manual_interaction_tag": "", "is_global_variable": false, "is_global_variable_persist": false, "global_variable_id": "", "mobile_browser": false, "wait_for_element_timeout": 0, "failure_condition": "Fail test immediately", "parent_instruction_id": "", "sub_instruction_obj": "{\"operation\": \"Assert 'invalid' text is visible on the viewport\", \"thought\": \"Verify that the 'invalid' text is present and visible on screen.\", \"agent\": \"Operation Agent\", \"operation_dict\": {\"operation_type\": \"ASSERTION\", \"assertion_tree\": {\"operator\": \"equals\", \"left_operand\": {\"invalid_visible\": \"runtime_variable\"}, \"right_operand\": {\"assertion_operand_98817bc0b00a4987a0d5826472439c6f_0\": \"runtime_variable\"}, \"transform_operands\": []}, \"operation_intent\": \"Assert 'invalid' text is visible on the viewport\"}, \"params\": {\"assertion_tree\": {\"operator\": \"equals\", \"left_operand\": {\"invalid_visible\": \"runtime_variable\"}, \"right_operand\": {\"assertion_operand_98817bc0b00a4987a0d5826472439c6f_0\": \"runtime_variable\"}, \"transform_operands\": []}, \"operation_intent\": \"Assert 'invalid' text is visible on the viewport\"}, \"secrets\": {}, \"variable\": {}}", "_original_index": 16, "global_operation_index": 16}, "9": {"operation_intent": "Click 'Reset' button", "locator": ["//html/body/div/div[1]/div[2]/div[2]/div/div[1]/div[2]/form/div[2]/button[1]"], "operation_type": "CLICK", "value": "", "instruction_id": "ad191aa9b39c45eb81df86ff1f9f043d", "operation_id": "57e1a2faab384ea7", "optional_flag": false, "max_retries": 0, "retries_delay": 0, "explicit_wait": 0, "implicit_wait": 0, "frame": "[]", "user_variables": "[]", "operation_start": "2025-09-13 14:34:44.473722", "operation_end": "2025-09-13 14:34:45.111553", "instruction_module_id": "", "instruction_module_name": "", "use_v2_mobile_tagging": false, "hard_assertion": false, "dialog_action": "", "dismiss_dialog": false, "is_coordinates_used_for_interaction": false, "element_coordinates_ratio": [], "element_bounds_ratio": [], "kaneaiMobileTaggingImageLimit": 1, "clicks_order_code": "se_js_ac", "selector": {"frameInfo": [], "locators": [{"isXPath": false, "score": 80, "selector": ".oxd-button--ghost"}, {"isXPath": false, "score": 80, "selector": ".oxd-button--medium.oxd-button--ghost"}, {"isXPath": true, "score": 70, "selector": "//div[@id='app']/div[1]/div[2]/div[2]/div[1]/div[1]/div[2]/form[1]/div[2]/button[1]"}, {"isXPath": false, "score": 65, "selector": "#app > div:nth-child(1) > div:nth-child(2) > div:nth-child(2) > div:nth-child(1) > div:nth-child(1) > div:nth-child(3) > form:nth-child(1) > div:nth-child(3) > button:nth-child(1)"}, {"isXPath": false, "score": 55, "selector": "button:has(+ [type=\"submit\"])"}, {"isXPath": true, "score": 40, "selector": "//button[contains(@class,'oxd-button--ghost')]"}, {"isXPath": true, "score": 25, "selector": "//button[contains(@class,'oxd-button--medium') and contains(@class,'oxd-button--ghost')]"}]}, "manual_interaction_tag": "", "is_global_variable": false, "is_global_variable_persist": false, "global_variable_id": "", "mobile_browser": false, "wait_for_element_timeout": 0, "failure_condition": "", "parent_instruction_id": "", "sub_instruction_obj": "{\"operation\": \"Click 'Reset' button\", \"thought\": \"Tap the element labeled 'Reset' on the page.\", \"agent\": \"Vision Agent\", \"operation_dict\": {\"operation_type\": \"CLICK\", \"element\": \"Reset\", \"operation_intent\": \"Click 'Reset' button\"}, \"params\": {}, \"secrets\": {}, \"variable\": {}}", "_original_index": 17, "global_operation_index": 17}}, "parameters": {"Anniversary_wishes": "wishing you happy Anniversary", "booking_category": "FACIAL TREATMENTS", "booking_note": "Note", "booking_service": "Fourhead", "booking_service_cost": "1000.00", "booking_service_duration": "150min", "Citrus_Illusion_cost": "72.00", "Citrus_Illusion_duration": "60min", "electronics": "Projector", "email": "demo@bank.test", "extra_gift_service": "FitSkin", "extra_gift_service_category": " SkinCare", "gift_delivery_hour": "06", "gift_delivery_option": "Send later", "gift_occasion": "Anniversary", "gift_recipient_name": "recipient_name", "new_user_DOB": "2000/12/12", "new_user_first_name": "first_name", "new_user_last_name": "last_name", "new_user_pass": "!#%246Qw", "password": "Correct$Horse7", "policyme_address": "2210 Sunset Cove Circle", "policyme_city": "Ontario", "policyme_country": "Canada", "policyme_dd": "13", "policyme_firstLegalName": "Vipul", "policyme_income": "100000", "policyme_lastLegalName": "Srivastava", "policyme_mm": "February", "policyme_yyyy": "1995", "services_list": "\"BODY TREATMENTS\" & \"PACKAGES\" & \"FLOAT\" & \"TREATMENTS\" & \"GROOMING SERVICES\" & \"HAIR SERVICES\" & \"LASER & BOTOX\" & \"MAKEUP\" & \"MESSAGE TREATMENTS\" & \"HANDS & FEET\" & \"SKIN CARE\" & \"SLIMMING\" & \"HAIR REMOVAL\" & \"FOOD\"", "Studio_name": "Demo_Center", "visaCard": "4111111111111111"}, "variables": {"username_input_box_visible": "true", "assertion_operand_664681c34fcc4d49bc7247e5de182e05_0": "true", "invalid_visible": "true", "assertion_operand_98817bc0b00a4987a0d5826472439c6f_0": "true"}, "global_variables": [{"id": 2505, "name": "advanced_analytics_value", "value": "true", "session_value": "true", "is_persist": false, "environment_id": 0, "environment_name": "No Env"}, {"id": 834, "name": "current_page_url_00651b", "value": "https://demo.zenoti.com/webstoreNew/guest/631ac7f2-a8c6-408c-93d7-3effb88f6643?location=0a36ed1d-0140-445a-ab17-7fcb8a14de97", "session_value": "https://demo.zenoti.com/webstoreNew/guest/631ac7f2-a8c6-408c-93d7-3effb88f6643?location=0a36ed1d-0140-445a-ab17-7fcb8a14de97", "is_persist": true, "environment_id": 0, "environment_name": "No Env"}, {"id": 1279, "name": "lambda_username", "value": "shantanuw", "session_value": "shantanuw", "is_persist": false, "environment_id": 0, "environment_name": "No Env"}, {"id": 832, "name": "page_url_a6df32", "value": "https://demo.zenoti.com/webstoreNew/services/thankyou?location=0a36ed1d-0140-445a-ab17-7fcb8a14de97", "session_value": "https://demo.zenoti.com/webstoreNew/services/thankyou?location=0a36ed1d-0140-445a-ab17-7fcb8a14de97", "is_persist": true, "environment_id": 0, "environment_name": "No Env"}, {"id": 15, "name": "trending_projector_price", "value": "false", "session_value": "false", "is_persist": true, "environment_id": 0, "environment_name": "No Env"}, {"id": 835, "name": "url_1", "value": "https://demo.zenoti.com/webstoreNew/guest/631ac7f2-a8c6-408c-93d7-3effb88f6643?location=0a36ed1d-0140-445a-ab17-7fcb8a14de97", "session_value": "https://demo.zenoti.com/webstoreNew/guest/631ac7f2-a8c6-408c-93d7-3effb88f6643?location=0a36ed1d-0140-445a-ab17-7fcb8a14de97", "is_persist": true, "environment_id": 0, "environment_name": "No Env"}, {"id": 1280, "name": "lt_username", "value": "shantanuw", "session_value": "shantanuw", "is_persist": false, "environment_id": 9, "environment_name": "prod"}, {"id": 1278, "name": "New", "value": "something", "session_value": "something", "is_persist": false, "environment_id": 9, "environment_name": "prod"}, {"id": 1258, "name": "page_url", "value": "https://www.lambdatest.com", "session_value": "https://www.lambdatest.com", "is_persist": false, "environment_id": 9, "environment_name": "prod"}, {"id": 3532, "name": "sap_url", "value": "https://my426318.s4hana.cloud.sap/ui?sap-language=EN#Shell-home", "session_value": "https://my426318.s4hana.cloud.sap/ui?sap-language=EN#Shell-home", "is_persist": false, "environment_id": 9, "environment_name": "prod"}, {"id": 887, "name": "Studio", "value": "demo_center", "session_value": "demo_center", "is_persist": false, "environment_id": 9, "environment_name": "prod"}, {"id": 57, "name": "url", "value": "https://accounts.lambdatest.com/login", "session_value": "https://accounts.lambdatest.com/login", "is_persist": false, "environment_id": 9, "environment_name": "prod"}, {"id": 18, "name": "username", "value": "shantanuw@lambdatest.com", "session_value": "shantanuw@lambdatest.com", "is_persist": false, "environment_id": 9, "environment_name": "prod"}, {"id": 20, "name": "username", "value": "swali@lambdatest.com", "session_value": "swali@lambdatest.com", "is_persist": false, "environment_id": 10, "environment_name": "stage"}, {"id": 2198, "name": "policyme_url", "value": "https://dev.policyme.com/life/life/intent", "session_value": "https://dev.policyme.com/life/life/intent", "is_persist": false, "environment_id": 289, "environment_name": "dev"}, {"id": 2272, "name": "policyme_url", "value": "https://dev.policyme.com/life/life/intent", "session_value": "https://dev.policyme.com/life/life/intent", "is_persist": false, "environment_id": 294, "environment_name": "policyme_test"}]}